copent/__init__.py
copent/copent.py
copent-0.5.7.dist-info/LICENSE
copent-0.5.7.dist-info/METADATA
copent-0.5.7.dist-info/WHEEL
copent-0.5.7.dist-info/top_level.txt
copent-0.5.7.dist-info/RECORD
