Metadata-Version: 2.1
Name: copent
Version: 0.5.7
Summary: Estimating Copula Entropy and Transfer Entropy
Home-page: https://github.com/majianthu/pycopent
Author: MA Jian
Author-email: majian03@gmail.com
License: GPL License
Requires-Python: >=2.7
License-File: LICENSE
Requires-Dist: numpy
Requires-Dist: scipy
